ip2geotools/__init__.py
ip2geotools/__main__.py
ip2geotools/cli.py
ip2geotools/errors.py
ip2geotools/models.py
ip2geotools/databases/__init__.py
ip2geotools/databases/commercial.py
ip2geotools/databases/interfaces.py
ip2geotools/databases/noncommercial.py
ip2geotools-0.1.4.dist-info/LICENSE
ip2geotools-0.1.4.dist-info/METADATA
ip2geotools-0.1.4.dist-info/WHEEL
ip2geotools-0.1.4.dist-info/entry_points.txt
ip2geotools-0.1.4.dist-info/top_level.txt
ip2geotools-0.1.4.dist-info/RECORD
