Metadata-Version: 2.1
Name: ip2geotools
Version: 0.1.4
Summary: Simple tool for getting geolocation information on given IP address from various geolocation databases.
Home-page: https://github.com/tomas-net/ip2geotools
Author: Tomas Caha
Author-email: tomas-net@seznam.cz
License: MIT License
Download-URL: https://github.com/tomas-net/ip2geotools/archive/0.1.4.tar.gz
Platform: UNKNOWN
Classifier: Development Status :: 5 - Production/Stable
Classifier: Environment :: Console
Classifier: Intended Audience :: Developers
Classifier: Intended Audience :: System Administrators
Classifier: Intended Audience :: Telecommunications Industry
Classifier: License :: OSI Approved :: MIT License
Classifier: Natural Language :: English
Classifier: Operating System :: POSIX :: Linux
Classifier: Programming Language :: Python
Classifier: Programming Language :: Python :: 3.3
Classifier: Programming Language :: Python :: 3.4
Classifier: Programming Language :: Python :: 3.5
Classifier: Programming Language :: Python :: 3.6
Classifier: Programming Language :: Python :: 3 :: Only
Classifier: Programming Language :: Python :: Implementation :: CPython
Classifier: Programming Language :: Python :: Implementation :: PyPy
Classifier: Topic :: Internet
Classifier: Topic :: Scientific/Engineering :: Information Analysis
Classifier: Topic :: Utilities
Requires-Dist: astroid (==2.1.0)
Requires-Dist: autopep8 (==1.4.3)
Requires-Dist: bleach (==3.0.2)
Requires-Dist: certifi (==2018.10.15)
Requires-Dist: chardet (==3.0.4)
Requires-Dist: Click (==7.0)
Requires-Dist: cssselect (==1.0.3)
Requires-Dist: decorator (==4.3.0)
Requires-Dist: dicttoxml (==1.7.4)
Requires-Dist: docutils (==0.14)
Requires-Dist: future (==0.17.1)
Requires-Dist: geocoder (==1.38.1)
Requires-Dist: geoip2 (==2.9.0)
Requires-Dist: idna (==2.7)
Requires-Dist: IP2Location (==8.0.3)
Requires-Dist: isort (==4.3.4)
Requires-Dist: lazy-object-proxy (==1.3.1)
Requires-Dist: lxml (==4.2.5)
Requires-Dist: maxminddb (==1.4.1)
Requires-Dist: mccabe (==0.6.1)
Requires-Dist: packaging (==18.0)
Requires-Dist: pip-review (==1.0)
Requires-Dist: pkginfo (==1.4.2)
Requires-Dist: pycodestyle (==2.4.0)
Requires-Dist: Pygments (==2.3.0)
Requires-Dist: pylint (==2.2.0)
Requires-Dist: pyparsing (==2.3.0)
Requires-Dist: pyquery (==1.4.0)
Requires-Dist: ratelim (==0.1.6)
Requires-Dist: readme-renderer (==24.0)
Requires-Dist: requests (==2.20.1)
Requires-Dist: requests-toolbelt (==0.8.0)
Requires-Dist: selenium (==3.141.0)
Requires-Dist: six (==1.11.0)
Requires-Dist: tqdm (==4.28.1)
Requires-Dist: twine (==1.12.1)
Requires-Dist: typed-ast (==1.1.0)
Requires-Dist: typing (==3.6.6)
Requires-Dist: urllib3 (==1.24.1)
Requires-Dist: webencodings (==0.5.1)
Requires-Dist: wrapt (==1.10.11)
